app/__init__.py
app/__main__.py
app/__version__.py
app/cli.py
covid_cli-1.0.8.dist-info/METADATA
covid_cli-1.0.8.dist-info/WHEEL
covid_cli-1.0.8.dist-info/entry_points.txt
covid_cli-1.0.8.dist-info/top_level.txt
covid_cli-1.0.8.dist-info/RECORD
