Metadata-Version: 2.1
Name: covid-cli
Version: 1.0.8
Summary: Get the latest COVID-19 information via the command line. 
Home-page: https://github.com/AnthonyBloomer/covid-cli
Author: Anthony Bloomer
Author-email: ant0@protonmail.ch
License: UNKNOWN
Keywords: coronavirus,covid19
Platform: UNKNOWN
Classifier: Development Status :: 5 - Production/Stable
Classifier: Environment :: Console
Classifier: Intended Audience :: Developers
Classifier: Intended Audience :: End Users/Desktop
Classifier: Operating System :: OS Independent
Classifier: License :: OSI Approved :: MIT License
Classifier: Programming Language :: Python
Classifier: Programming Language :: Python :: 2.7
Classifier: Programming Language :: Python :: 3
Classifier: Programming Language :: Python :: 3.3
Classifier: Programming Language :: Python :: 3.4
Classifier: Programming Language :: Python :: 3.5
Classifier: Programming Language :: Python :: 3.6
Requires-Dist: requests
Requires-Dist: PTable
Requires-Dist: pandas
